Metadata-Version: 2.1
Name: odoo-addon-hr_personal_equipment_request
Version: 18.0.1.0.0.2
Requires-Python: >=3.10
Requires-Dist: odoo==18.0.*
Summary: This addon allows to manage employee personal equipment
Home-page: https://github.com/OCA/hr
License: AGPL-3
Author: Creu Blanca, Odoo Community Association (OCA)
Author-email: support@odoo-community.org
Classifier: Programming Language :: Python
Classifier: Framework :: Odoo
Classifier: Framework :: Odoo :: 18.0
Classifier: License :: OSI Approved :: GNU Affero General Public License v3
